[
  {
    "name": "aggregate-count",
    "value": 0,
    "random": 0.6844,
    "structured": 0.5773
  },
  {
    "name": "aggregate-count",
    "value": 1,
    "random": 0.30535,
    "structured": 0.41245
  },
  {
    "name": "aggregate-count",
    "value": 3,
    "random": 0.01025,
    "structured": 0.01015
  },
  {
    "name": "aggregate-sum",
    "value": 0,
    "random": 0.9964,
    "structured": 0.7914
  },
  {
    "name": "aggregate-sum",
    "value": 1,
    "random": 0.00225,
    "structured": 0.16295
  },
  {
    "name": "aggregate-sum",
    "value": 2,
    "random": 0.0013,
    "structured": 0.0369
  },
  {
    "name": "aggregate-sum",
    "value": 3,
    "random": 0.00005,
    "structured": 0.00845
  },
  {
    "name": "aggregate-mean",
    "value": 0,
    "random": 0.8806,
    "structured": 0.9438
  },
  {
    "name": "aggregate-mean",
    "value": 1,
    "random": 0.0912,
    "structured": 0.04175
  },
  {
    "name": "aggregate-mean",
    "value": 2,
    "random": 0.02475,
    "structured": 0.0115
  },
  {
    "name": "aggregate-mean",
    "value": 3,
    "random": 0.00315,
    "structured": 0.0029
  },
  {
    "name": "aggregate-mean",
    "value": 4,
    "random": 0.0003,
    "structured": 0.00005
  },
  {
    "name": "aggregate-median",
    "value": 0,
    "random": 0.8501,
    "structured": 0.7337
  },
  {
    "name": "aggregate-median",
    "value": 1,
    "random": 0.0822,
    "structured": 0.1783
  },
  {
    "name": "aggregate-median",
    "value": 2,
    "random": 0.04635,
    "structured": 0.0649
  },
  {
    "name": "aggregate-median",
    "value": 3,
    "random": 0.01805,
    "structured": 0.02235
  },
  {
    "name": "aggregate-median",
    "value": 4,
    "random": 0.0033,
    "structured": 0.00075
  },
  {
    "name": "aggregate-min",
    "value": 0,
    "random": 0.9552,
    "structured": 0.7836
  },
  {
    "name": "aggregate-min",
    "value": 1,
    "random": 0.02885,
    "structured": 0.15325
  },
  {
    "name": "aggregate-min",
    "value": 2,
    "random": 0.0133,
    "structured": 0.04635
  },
  {
    "name": "aggregate-min",
    "value": 3,
    "random": 0.00245,
    "structured": 0.0158
  },
  {
    "name": "aggregate-min",
    "value": 4,
    "random": 0.0002,
    "structured": 0.001
  },
  {
    "name": "aggregate-max",
    "value": 0,
    "random": 0.9996,
    "structured": 0.8875
  },
  {
    "name": "aggregate-max",
    "value": 1,
    "random": 0.0002,
    "structured": 0.07705
  },
  {
    "name": "aggregate-max",
    "value": 2,
    "random": 0.00015,
    "structured": 0.02685
  },
  {
    "name": "aggregate-max",
    "value": 3,
    "random": 0.00005,
    "structured": 0.0081
  },
  {
    "name": "aggregate-stdev",
    "value": 0,
    "random": 1,
    "structured": 0.9486
  },
  {
    "name": "chart-only_x_over_only_y",
    "value": 0,
    "random": 0.95505,
    "structured": 0.9135
  },
  {
    "name": "chart-only_x_over_only_y",
    "value": 1,
    "random": 0.04495,
    "structured": 0.0865
  },
  {
    "name": "chart-binned_one_dimensional",
    "value": 0,
    "random": 0.9786,
    "structured": 0.9991
  },
  {
    "name": "chart-binned_one_dimensional",
    "value": 1,
    "random": 0.0214,
    "structured": 0.0009
  },
  {
    "name": "chart-orientation_horizontal_binned",
    "value": 0,
    "random": 0.8581,
    "structured": 0.833
  },
  {
    "name": "chart-orientation_horizontal_binned",
    "value": 1,
    "random": 0.1419,
    "structured": 0.167
  },
  {
    "name": "chart-one_dim_raw_continuous_tick_over_rest",
    "value": 0,
    "random": 0.9588,
    "structured": 0.99505
  },
  {
    "name": "chart-one_dim_raw_continuous_tick_over_rest",
    "value": 1,
    "random": 0.0412,
    "structured": 0.00495
  },
  {
    "name": "datatype-string_quantitative",
    "value": 0,
    "random": 1,
    "structured": 1
  },
  {
    "name": "datatype-string_ordinal",
    "value": 0,
    "random": 0.754,
    "structured": 0.8631
  },
  {
    "name": "datatype-string_ordinal",
    "value": 1,
    "random": 0.1393,
    "structured": 0.0935
  },
  {
    "name": "datatype-string_ordinal",
    "value": 2,
    "random": 0.0665,
    "structured": 0.03145
  },
  {
    "name": "datatype-string_ordinal",
    "value": 3,
    "random": 0.03345,
    "structured": 0.0115
  },
  {
    "name": "datatype-string_ordinal",
    "value": 4,
    "random": 0.00675,
    "structured": 0.00045
  },
  {
    "name": "datatype-string_nominal",
    "value": 0,
    "random": 0.8764,
    "structured": 0.8588
  },
  {
    "name": "datatype-string_nominal",
    "value": 1,
    "random": 0.0734,
    "structured": 0.11145
  },
  {
    "name": "datatype-string_nominal",
    "value": 2,
    "random": 0.0362,
    "structured": 0.0241
  },
  {
    "name": "datatype-string_nominal",
    "value": 3,
    "random": 0.0135,
    "structured": 0.00555
  },
  {
    "name": "datatype-string_nominal",
    "value": 4,
    "random": 0.0005,
    "structured": 0.0001
  },
  {
    "name": "datatype-string_temporal",
    "value": 0,
    "random": 1,
    "structured": 1
  },
  {
    "name": "datatype-number_quantitative",
    "value": 0,
    "random": 0.7662,
    "structured": 0.7408
  },
  {
    "name": "datatype-number_quantitative",
    "value": 1,
    "random": 0.1207,
    "structured": 0.16965
  },
  {
    "name": "datatype-number_quantitative",
    "value": 2,
    "random": 0.07155,
    "structured": 0.0668
  },
  {
    "name": "datatype-number_quantitative",
    "value": 3,
    "random": 0.0328,
    "structured": 0.0206
  },
  {
    "name": "datatype-number_quantitative",
    "value": 4,
    "random": 0.00875,
    "structured": 0.00215
  },
  {
    "name": "datatype-number_ordinal",
    "value": 0,
    "random": 0.9019,
    "structured": 0.901
  },
  {
    "name": "datatype-number_ordinal",
    "value": 1,
    "random": 0.0636,
    "structured": 0.0695
  },
  {
    "name": "datatype-number_ordinal",
    "value": 2,
    "random": 0.02695,
    "structured": 0.0233
  },
  {
    "name": "datatype-number_ordinal",
    "value": 3,
    "random": 0.00705,
    "structured": 0.006
  },
  {
    "name": "datatype-number_ordinal",
    "value": 4,
    "random": 0.0005,
    "structured": 0.0002
  },
  {
    "name": "datatype-number_nominal",
    "value": 0,
    "random": 0.8911,
    "structured": 0.8934
  },
  {
    "name": "datatype-number_nominal",
    "value": 1,
    "random": 0.07025,
    "structured": 0.08175
  },
  {
    "name": "datatype-number_nominal",
    "value": 2,
    "random": 0.0287,
    "structured": 0.0199
  },
  {
    "name": "datatype-number_nominal",
    "value": 3,
    "random": 0.00945,
    "structured": 0.00475
  },
  {
    "name": "datatype-number_nominal",
    "value": 4,
    "random": 0.0005,
    "structured": 0.0002
  },
  {
    "name": "datatype-number_temporal",
    "value": 0,
    "random": 1,
    "structured": 1
  },
  {
    "name": "datatype-integer_quantitative",
    "value": 0,
    "random": 0.9344,
    "structured": 0.8154
  },
  {
    "name": "datatype-integer_quantitative",
    "value": 1,
    "random": 0.03915,
    "structured": 0.1152
  },
  {
    "name": "datatype-integer_quantitative",
    "value": 2,
    "random": 0.0183,
    "structured": 0.04815
  },
  {
    "name": "datatype-integer_quantitative",
    "value": 3,
    "random": 0.0073,
    "structured": 0.0185
  },
  {
    "name": "datatype-integer_quantitative",
    "value": 4,
    "random": 0.00085,
    "structured": 0.00275
  },
  {
    "name": "datatype-integer_ordinal",
    "value": 0,
    "random": 0.9562,
    "structured": 0.9082
  },
  {
    "name": "datatype-integer_ordinal",
    "value": 1,
    "random": 0.0305,
    "structured": 0.06095
  },
  {
    "name": "datatype-integer_ordinal",
    "value": 2,
    "random": 0.0111,
    "structured": 0.02205
  },
  {
    "name": "datatype-integer_ordinal",
    "value": 3,
    "random": 0.00215,
    "structured": 0.00875
  },
  {
    "name": "datatype-integer_ordinal",
    "value": 4,
    "random": 0.00005,
    "structured": 0.00005
  },
  {
    "name": "datatype-integer_nominal",
    "value": 0,
    "random": 0.9545,
    "structured": 0.9053
  },
  {
    "name": "datatype-integer_nominal",
    "value": 1,
    "random": 0.0312,
    "structured": 0.0692
  },
  {
    "name": "datatype-integer_nominal",
    "value": 2,
    "random": 0.0113,
    "structured": 0.0202
  },
  {
    "name": "datatype-integer_nominal",
    "value": 3,
    "random": 0.00275,
    "structured": 0.00515
  },
  {
    "name": "datatype-integer_nominal",
    "value": 4,
    "random": 0.00025,
    "structured": 0.00015
  },
  {
    "name": "datatype-integer_temporal",
    "value": 0,
    "random": 1,
    "structured": 1
  },
  {
    "name": "datatype-boolean_quantitative",
    "value": 0,
    "random": 1,
    "structured": 1
  },
  {
    "name": "datatype-boolean_ordinal",
    "value": 0,
    "random": 0.9706,
    "structured": 0.9171
  },
  {
    "name": "datatype-boolean_ordinal",
    "value": 1,
    "random": 0.01865,
    "structured": 0.05035
  },
  {
    "name": "datatype-boolean_ordinal",
    "value": 2,
    "random": 0.0082,
    "structured": 0.02305
  },
  {
    "name": "datatype-boolean_ordinal",
    "value": 3,
    "random": 0.00245,
    "structured": 0.00915
  },
  {
    "name": "datatype-boolean_ordinal",
    "value": 4,
    "random": 0.0001,
    "structured": 0.00035
  },
  {
    "name": "datatype-boolean_nominal",
    "value": 0,
    "random": 0.9793,
    "structured": 0.9454
  },
  {
    "name": "datatype-boolean_nominal",
    "value": 1,
    "random": 0.01335,
    "structured": 0.0387
  },
  {
    "name": "datatype-boolean_nominal",
    "value": 2,
    "random": 0.00565,
    "structured": 0.01175
  },
  {
    "name": "datatype-boolean_nominal",
    "value": 3,
    "random": 0.00165,
    "structured": 0.00405
  },
  {
    "name": "datatype-boolean_nominal",
    "value": 4,
    "random": 0.00005,
    "structured": 0.0001
  },
  {
    "name": "datatype-boolean_temporal",
    "value": 0,
    "random": 1,
    "structured": 1
  },
  {
    "name": "datatype-date_quantitative",
    "value": 0,
    "random": 0.873,
    "structured": 0.735
  },
  {
    "name": "datatype-date_quantitative",
    "value": 1,
    "random": 0.07385,
    "structured": 0.1721
  },
  {
    "name": "datatype-date_quantitative",
    "value": 2,
    "random": 0.0365,
    "structured": 0.0659
  },
  {
    "name": "datatype-date_quantitative",
    "value": 3,
    "random": 0.01445,
    "structured": 0.0248
  },
  {
    "name": "datatype-date_quantitative",
    "value": 4,
    "random": 0.0022,
    "structured": 0.0022
  },
  {
    "name": "datatype-date_ordinal",
    "value": 0,
    "random": 0.9286,
    "structured": 0.8898
  },
  {
    "name": "datatype-date_ordinal",
    "value": 1,
    "random": 0.04585,
    "structured": 0.074
  },
  {
    "name": "datatype-date_ordinal",
    "value": 2,
    "random": 0.01995,
    "structured": 0.0275
  },
  {
    "name": "datatype-date_ordinal",
    "value": 3,
    "random": 0.00535,
    "structured": 0.0085
  },
  {
    "name": "datatype-date_ordinal",
    "value": 4,
    "random": 0.00025,
    "structured": 0.0002
  },
  {
    "name": "datatype-date_nominal",
    "value": 0,
    "random": 0.9191,
    "structured": 0.8879
  },
  {
    "name": "datatype-date_nominal",
    "value": 1,
    "random": 0.05435,
    "structured": 0.0846
  },
  {
    "name": "datatype-date_nominal",
    "value": 2,
    "random": 0.0219,
    "structured": 0.0228
  },
  {
    "name": "datatype-date_nominal",
    "value": 3,
    "random": 0.0044,
    "structured": 0.0047
  },
  {
    "name": "datatype-date_nominal",
    "value": 4,
    "random": 0.00025,
    "structured": 0
  },
  {
    "name": "datatype-date_temporal",
    "value": 0,
    "random": 0.8824,
    "structured": 0.7888
  },
  {
    "name": "datatype-date_temporal",
    "value": 1,
    "random": 0.08215,
    "structured": 0.16255
  },
  {
    "name": "datatype-date_temporal",
    "value": 2,
    "random": 0.0295,
    "structured": 0.03765
  },
  {
    "name": "datatype-date_temporal",
    "value": 3,
    "random": 0.00565,
    "structured": 0.01
  },
  {
    "name": "datatype-date_temporal",
    "value": 4,
    "random": 0.0003,
    "structured": 0.001
  },
  {
    "name": "datatype-high_cardinality_ordinal",
    "value": 0,
    "random": 0.7763,
    "structured": 0.7604
  },
  {
    "name": "datatype-high_cardinality_ordinal",
    "value": 1,
    "random": 0.13195,
    "structured": 0.15995
  },
  {
    "name": "datatype-high_cardinality_ordinal",
    "value": 2,
    "random": 0.0668,
    "structured": 0.0613
  },
  {
    "name": "datatype-high_cardinality_ordinal",
    "value": 3,
    "random": 0.02195,
    "structured": 0.01795
  },
  {
    "name": "datatype-high_cardinality_ordinal",
    "value": 4,
    "random": 0.003,
    "structured": 0.0004
  },
  {
    "name": "datatype-high_cardinality_nominal",
    "value": 0,
    "random": 0.7705,
    "structured": 0.7212
  },
  {
    "name": "datatype-high_cardinality_nominal",
    "value": 1,
    "random": 0.1451,
    "structured": 0.20655
  },
  {
    "name": "datatype-high_cardinality_nominal",
    "value": 2,
    "random": 0.0629,
    "structured": 0.05935
  },
  {
    "name": "datatype-high_cardinality_nominal",
    "value": 3,
    "random": 0.0202,
    "structured": 0.0127
  },
  {
    "name": "datatype-high_cardinality_nominal",
    "value": 4,
    "random": 0.0013,
    "structured": 0.0002
  },
  {
    "name": "datatype-high_cardinality_nominal_color",
    "value": 0,
    "random": 1,
    "structured": 1
  },
  {
    "name": "datatype-high_cardinality_size",
    "value": 0,
    "random": 1,
    "structured": 1
  },
  {
    "name": "encoding-encoding",
    "value": 1,
    "random": 0.2531,
    "structured": 0.0174
  },
  {
    "name": "encoding-encoding",
    "value": 2,
    "random": 0.2504,
    "structured": 0.2071
  },
  {
    "name": "encoding-encoding",
    "value": 3,
    "random": 0.2505,
    "structured": 0.382
  },
  {
    "name": "encoding-encoding",
    "value": 4,
    "random": 0.246,
    "structured": 0.3935
  },
  {
    "name": "encoding-encoding_field",
    "value": 0,
    "random": 0.0064,
    "structured": 0.001
  },
  {
    "name": "encoding-encoding_field",
    "value": 1,
    "random": 0.314,
    "structured": 0.06905
  },
  {
    "name": "encoding-encoding_field",
    "value": 2,
    "random": 0.2981,
    "structured": 0.33125
  },
  {
    "name": "encoding-encoding_field",
    "value": 3,
    "random": 0.2829,
    "structured": 0.41805
  },
  {
    "name": "encoding-encoding_field",
    "value": 4,
    "random": 0.0986,
    "structured": 0.18065
  },
  {
    "name": "encoding-aggregate",
    "value": 0,
    "random": 0.45725,
    "structured": 0.1361
  },
  {
    "name": "encoding-aggregate",
    "value": 1,
    "random": 0.3789,
    "structured": 0.34745
  },
  {
    "name": "encoding-aggregate",
    "value": 2,
    "random": 0.0909,
    "structured": 0.27735
  },
  {
    "name": "encoding-aggregate",
    "value": 3,
    "random": 0.05355,
    "structured": 0.1753
  },
  {
    "name": "encoding-aggregate",
    "value": 4,
    "random": 0.0194,
    "structured": 0.0638
  },
  {
    "name": "encoding-bin",
    "value": 0,
    "random": 0.7935,
    "structured": 0.6335
  },
  {
    "name": "encoding-bin",
    "value": 1,
    "random": 0.12535,
    "structured": 0.24865
  },
  {
    "name": "encoding-bin",
    "value": 2,
    "random": 0.0595,
    "structured": 0.0871
  },
  {
    "name": "encoding-bin",
    "value": 3,
    "random": 0.0196,
    "structured": 0.0297
  },
  {
    "name": "encoding-bin",
    "value": 4,
    "random": 0.00205,
    "structured": 0.00105
  },
  {
    "name": "encoding-same_field_2",
    "value": 0,
    "random": 0.60415,
    "structured": 0.61965
  },
  {
    "name": "encoding-same_field_2",
    "value": 1,
    "random": 0.3791,
    "structured": 0.3644
  },
  {
    "name": "encoding-same_field_2",
    "value": 2,
    "random": 0.01675,
    "structured": 0.01595
  },
  {
    "name": "encoding-same_field_gte3",
    "value": 0,
    "random": 0.9263,
    "structured": 0.88565
  },
  {
    "name": "encoding-same_field_gte3",
    "value": 1,
    "random": 0.0737,
    "structured": 0.11435
  },
  {
    "name": "encoding-count_twice",
    "value": 0,
    "random": 0.98975,
    "structured": 0.98975
  },
  {
    "name": "encoding-count_twice",
    "value": 1,
    "random": 0.01025,
    "structured": 0.01025
  },
  {
    "name": "encoding-quant_bin",
    "value": 0,
    "random": 0.9678,
    "structured": 0.8283
  },
  {
    "name": "encoding-quant_bin",
    "value": 1,
    "random": 0.02035,
    "structured": 0.1184
  },
  {
    "name": "encoding-quant_bin",
    "value": 2,
    "random": 0.0093,
    "structured": 0.04075
  },
  {
    "name": "encoding-quant_bin",
    "value": 3,
    "random": 0.00245,
    "structured": 0.0121
  },
  {
    "name": "encoding-quant_bin",
    "value": 4,
    "random": 0.0001,
    "structured": 0.00045
  },
  {
    "name": "encoding-non_positional_pref",
    "value": 0,
    "random": 0.7971,
    "structured": 0.7459
  },
  {
    "name": "encoding-non_positional_pref",
    "value": 1,
    "random": 0.2029,
    "structured": 0.2541
  },
  {
    "name": "encoding-multiple_non_pos",
    "value": 0,
    "random": 0.82535,
    "structured": 0.6456
  },
  {
    "name": "encoding-multiple_non_pos",
    "value": 1,
    "random": 0.17465,
    "structured": 0.3544
  },
  {
    "name": "encoding-aggregate_group_by_raw_non_temporal",
    "value": 0,
    "random": 0.9021,
    "structured": 0.898
  },
  {
    "name": "encoding-aggregate_group_by_raw_non_temporal",
    "value": 1,
    "random": 0.05265,
    "structured": 0.08255
  },
  {
    "name": "encoding-aggregate_group_by_raw_non_temporal",
    "value": 2,
    "random": 0.03375,
    "structured": 0.0167
  },
  {
    "name": "encoding-aggregate_group_by_raw_non_temporal",
    "value": 3,
    "random": 0.0115,
    "structured": 0.00275
  },
  {
    "name": "encoding-agg_dim",
    "value": 0,
    "random": 0.9168,
    "structured": 0.912
  },
  {
    "name": "encoding-agg_dim",
    "value": 1,
    "random": 0.0832,
    "structured": 0.088
  },
  {
    "name": "encoding-x_y_raw",
    "value": 0,
    "random": 0.9939,
    "structured": 0.9789
  },
  {
    "name": "encoding-x_y_raw",
    "value": 1,
    "random": 0.00515,
    "structured": 0.02
  },
  {
    "name": "encoding-x_y_raw",
    "value": 2,
    "random": 0.00095,
    "structured": 0.0011
  },
  {
    "name": "encoding-stack_zero",
    "value": 0,
    "random": 0.99665,
    "structured": 0.9653
  },
  {
    "name": "encoding-stack_zero",
    "value": 1,
    "random": 0.00335,
    "structured": 0.0347
  },
  {
    "name": "encoding-stack_normalize",
    "value": 0,
    "random": 0.9953,
    "structured": 0.9829
  },
  {
    "name": "encoding-stack_normalize",
    "value": 1,
    "random": 0.0047,
    "structured": 0.0171
  },
  {
    "name": "encoding-type_quantitative",
    "value": 0,
    "random": 0.39885,
    "structured": 0.1418
  },
  {
    "name": "encoding-type_quantitative",
    "value": 1,
    "random": 0.3396,
    "structured": 0.43095
  },
  {
    "name": "encoding-type_quantitative",
    "value": 2,
    "random": 0.1322,
    "structured": 0.26225
  },
  {
    "name": "encoding-type_quantitative",
    "value": 3,
    "random": 0.08805,
    "structured": 0.1334
  },
  {
    "name": "encoding-type_quantitative",
    "value": 4,
    "random": 0.0413,
    "structured": 0.0316
  },
  {
    "name": "encoding-type_ordinal",
    "value": 0,
    "random": 0.5327,
    "structured": 0.4963
  },
  {
    "name": "encoding-type_ordinal",
    "value": 1,
    "random": 0.268,
    "structured": 0.3191
  },
  {
    "name": "encoding-type_ordinal",
    "value": 2,
    "random": 0.1304,
    "structured": 0.1348
  },
  {
    "name": "encoding-type_ordinal",
    "value": 3,
    "random": 0.05915,
    "structured": 0.0482
  },
  {
    "name": "encoding-type_ordinal",
    "value": 4,
    "random": 0.00975,
    "structured": 0.0016
  },
  {
    "name": "encoding-type_nominal",
    "value": 0,
    "random": 0.6359,
    "structured": 0.5025
  },
  {
    "name": "encoding-type_nominal",
    "value": 1,
    "random": 0.2209,
    "structured": 0.3651
  },
  {
    "name": "encoding-type_nominal",
    "value": 2,
    "random": 0.10195,
    "structured": 0.1051
  },
  {
    "name": "encoding-type_nominal",
    "value": 3,
    "random": 0.0383,
    "structured": 0.0265
  },
  {
    "name": "encoding-type_nominal",
    "value": 4,
    "random": 0.00295,
    "structured": 0.0008
  },
  {
    "name": "mark_type-c_c_point",
    "value": 0,
    "random": 0.94855,
    "structured": 0.93605
  },
  {
    "name": "mark_type-c_c_point",
    "value": 1,
    "random": 0.05145,
    "structured": 0.06395
  },
  {
    "name": "mark_type-c_c_circle",
    "value": 0,
    "random": 1,
    "structured": 1
  },
  {
    "name": "mark_type-c_c_square",
    "value": 0,
    "random": 1,
    "structured": 1
  },
  {
    "name": "mark_type-c_c_line",
    "value": 0,
    "random": 0.97895,
    "structured": 0.97515
  },
  {
    "name": "mark_type-c_c_line",
    "value": 1,
    "random": 0.02105,
    "structured": 0.02485
  },
  {
    "name": "mark_type-c_c_area",
    "value": 0,
    "random": 1,
    "structured": 1
  },
  {
    "name": "mark_type-c_c_text",
    "value": 0,
    "random": 0.99145,
    "structured": 0.96165
  },
  {
    "name": "mark_type-c_c_text",
    "value": 1,
    "random": 0.00855,
    "structured": 0.03835
  },
  {
    "name": "mark_type-c_c_tick",
    "value": 0,
    "random": 1,
    "structured": 1
  },
  {
    "name": "mark_type-c_d_point",
    "value": 0,
    "random": 0.8932,
    "structured": 0.89195
  },
  {
    "name": "mark_type-c_d_point",
    "value": 1,
    "random": 0.1068,
    "structured": 0.10805
  },
  {
    "name": "mark_type-c_d_bar",
    "value": 0,
    "random": 1,
    "structured": 1
  },
  {
    "name": "mark_type-c_d_line",
    "value": 0,
    "random": 0.9978,
    "structured": 0.9657
  },
  {
    "name": "mark_type-c_d_line",
    "value": 1,
    "random": 0.0022,
    "structured": 0.0343
  },
  {
    "name": "mark_type-c_d_area",
    "value": 0,
    "random": 1,
    "structured": 1
  },
  {
    "name": "mark_type-c_d_text",
    "value": 0,
    "random": 0.9857,
    "structured": 0.94485
  },
  {
    "name": "mark_type-c_d_text",
    "value": 1,
    "random": 0.0143,
    "structured": 0.05515
  },
  {
    "name": "mark_type-c_d_tick",
    "value": 0,
    "random": 0.9982,
    "structured": 0.9689
  },
  {
    "name": "mark_type-c_d_tick",
    "value": 1,
    "random": 0.0018,
    "structured": 0.0311
  },
  {
    "name": "mark_type-c_d_no_overlap_point",
    "value": 0,
    "random": 0.84725,
    "structured": 0.92205
  },
  {
    "name": "mark_type-c_d_no_overlap_point",
    "value": 1,
    "random": 0.15275,
    "structured": 0.07795
  },
  {
    "name": "mark_type-c_d_no_overlap_bar",
    "value": 0,
    "random": 0.984,
    "structured": 0.9428
  },
  {
    "name": "mark_type-c_d_no_overlap_bar",
    "value": 1,
    "random": 0.016,
    "structured": 0.0572
  },
  {
    "name": "mark_type-c_d_no_overlap_line",
    "value": 0,
    "random": 0.99745,
    "structured": 0.97255
  },
  {
    "name": "mark_type-c_d_no_overlap_line",
    "value": 1,
    "random": 0.00255,
    "structured": 0.02745
  },
  {
    "name": "mark_type-c_d_no_overlap_area",
    "value": 0,
    "random": 0.9965,
    "structured": 0.97205
  },
  {
    "name": "mark_type-c_d_no_overlap_area",
    "value": 1,
    "random": 0.0035,
    "structured": 0.02795
  },
  {
    "name": "mark_type-c_d_no_overlap_text",
    "value": 0,
    "random": 0.9963,
    "structured": 0.96215
  },
  {
    "name": "mark_type-c_d_no_overlap_text",
    "value": 1,
    "random": 0.0037,
    "structured": 0.03785
  },
  {
    "name": "mark_type-c_d_no_overlap_tick",
    "value": 0,
    "random": 0.99755,
    "structured": 0.97085
  },
  {
    "name": "mark_type-c_d_no_overlap_tick",
    "value": 1,
    "random": 0.00245,
    "structured": 0.02915
  },
  {
    "name": "mark_type-d_d_point",
    "value": 0,
    "random": 0.85095,
    "structured": 0.9403
  },
  {
    "name": "mark_type-d_d_point",
    "value": 1,
    "random": 0.14905,
    "structured": 0.0597
  },
  {
    "name": "mark_type-d_d_text",
    "value": 0,
    "random": 0.97985,
    "structured": 0.96285
  },
  {
    "name": "mark_type-d_d_text",
    "value": 1,
    "random": 0.02015,
    "structured": 0.03715
  },
  {
    "name": "mark_type-d_d_rect",
    "value": 0,
    "random": 1,
    "structured": 1
  },
  {
    "name": "scale-log",
    "value": 0,
    "random": 1,
    "structured": 0.39265
  },
  {
    "name": "scale-zero",
    "value": 0,
    "random": 0.5153,
    "structured": 0.2477
  },
  {
    "name": "scale-zero",
    "value": 1,
    "random": 0.3424,
    "structured": 0.4481
  },
  {
    "name": "scale-zero",
    "value": 2,
    "random": 0.0854,
    "structured": 0.2145
  },
  {
    "name": "scale-zero",
    "value": 3,
    "random": 0.0471,
    "structured": 0.079
  },
  {
    "name": "scale-zero",
    "value": 4,
    "random": 0.0098,
    "structured": 0.0107
  },
  {
    "name": "scale-zero_bin",
    "value": 0,
    "random": 1,
    "structured": 1
  },
  {
    "name": "scale-zero_size",
    "value": 0,
    "random": 0.87605,
    "structured": 0.74455
  },
  {
    "name": "scale-zero_size",
    "value": 1,
    "random": 0.12395,
    "structured": 0.25545
  },
  {
    "name": "scale-zero_positional",
    "value": 0,
    "random": 0.65125,
    "structured": 0.4242
  },
  {
    "name": "scale-zero_positional",
    "value": 1,
    "random": 0.34875,
    "structured": 0.5758
  },
  {
    "name": "scale-zero_skew",
    "value": 0,
    "random": 0.92915,
    "structured": 0.8733
  },
  {
    "name": "scale-zero_skew",
    "value": 1,
    "random": 0.07085,
    "structured": 0.1267
  },
  {
    "name": "scale-includes_zero",
    "value": 0,
    "random": 0.9407,
    "structured": 0.89905
  },
  {
    "name": "scale-includes_zero",
    "value": 1,
    "random": 0.0506,
    "structured": 0.0886
  },
  {
    "name": "scale-includes_zero",
    "value": 2,
    "random": 0.00745,
    "structured": 0.0115
  },
  {
    "name": "scale-includes_zero",
    "value": 3,
    "random": 0.00125,
    "structured": 0.0008
  },
  {
    "name": "type_channel-continuous_x",
    "value": 0,
    "random": 0.6206,
    "structured": 0.4395
  },
  {
    "name": "type_channel-continuous_x",
    "value": 1,
    "random": 0.3794,
    "structured": 0.5605
  },
  {
    "name": "type_channel-continuous_y",
    "value": 0,
    "random": 0.8208,
    "structured": 0.66985
  },
  {
    "name": "type_channel-continuous_y",
    "value": 1,
    "random": 0.1792,
    "structured": 0.33015
  },
  {
    "name": "type_channel-continuous_color",
    "value": 0,
    "random": 0.773,
    "structured": 0.68105
  },
  {
    "name": "type_channel-continuous_color",
    "value": 1,
    "random": 0.227,
    "structured": 0.31895
  },
  {
    "name": "type_channel-continuous_size",
    "value": 0,
    "random": 0.9056,
    "structured": 0.8616
  },
  {
    "name": "type_channel-continuous_size",
    "value": 1,
    "random": 0.0944,
    "structured": 0.1384
  },
  {
    "name": "type_channel-continuous_text",
    "value": 0,
    "random": 0.952,
    "structured": 0.87225
  },
  {
    "name": "type_channel-continuous_text",
    "value": 1,
    "random": 0.048,
    "structured": 0.12775
  },
  {
    "name": "type_channel-ordered_x",
    "value": 0,
    "random": 0.6638,
    "structured": 0.79755
  },
  {
    "name": "type_channel-ordered_x",
    "value": 1,
    "random": 0.3362,
    "structured": 0.20245
  },
  {
    "name": "type_channel-ordered_y",
    "value": 0,
    "random": 0.72065,
    "structured": 0.7039
  },
  {
    "name": "type_channel-ordered_y",
    "value": 1,
    "random": 0.27935,
    "structured": 0.2961
  },
  {
    "name": "type_channel-ordered_color",
    "value": 0,
    "random": 0.9296,
    "structured": 0.87085
  },
  {
    "name": "type_channel-ordered_color",
    "value": 1,
    "random": 0.0704,
    "structured": 0.12915
  },
  {
    "name": "type_channel-ordered_size",
    "value": 0,
    "random": 0.95195,
    "structured": 0.86725
  },
  {
    "name": "type_channel-ordered_size",
    "value": 1,
    "random": 0.04805,
    "structured": 0.13275
  },
  {
    "name": "type_channel-ordered_text",
    "value": 0,
    "random": 0.9381,
    "structured": 0.89795
  },
  {
    "name": "type_channel-ordered_text",
    "value": 1,
    "random": 0.0619,
    "structured": 0.10205
  },
  {
    "name": "type_channel-ordered_row",
    "value": 0,
    "random": 0.88745,
    "structured": 0.89355
  },
  {
    "name": "type_channel-ordered_row",
    "value": 1,
    "random": 0.11255,
    "structured": 0.10645
  },
  {
    "name": "type_channel-ordered_column",
    "value": 0,
    "random": 0.89855,
    "structured": 0.9511
  },
  {
    "name": "type_channel-ordered_column",
    "value": 1,
    "random": 0.10145,
    "structured": 0.0489
  },
  {
    "name": "type_channel-nominal_x",
    "value": 0,
    "random": 0.8118,
    "structured": 0.88245
  },
  {
    "name": "type_channel-nominal_x",
    "value": 1,
    "random": 0.1882,
    "structured": 0.11755
  },
  {
    "name": "type_channel-nominal_y",
    "value": 0,
    "random": 0.8573,
    "structured": 0.8296
  },
  {
    "name": "type_channel-nominal_y",
    "value": 1,
    "random": 0.1427,
    "structured": 0.1704
  },
  {
    "name": "type_channel-nominal_color",
    "value": 0,
    "random": 0.96955,
    "structured": 0.9059
  },
  {
    "name": "type_channel-nominal_color",
    "value": 1,
    "random": 0.03045,
    "structured": 0.0941
  },
  {
    "name": "type_channel-nominal_shape",
    "value": 0,
    "random": 0.9812,
    "structured": 0.9601
  },
  {
    "name": "type_channel-nominal_shape",
    "value": 1,
    "random": 0.0188,
    "structured": 0.0399
  },
  {
    "name": "type_channel-nominal_text",
    "value": 0,
    "random": 0.9665,
    "structured": 0.91775
  },
  {
    "name": "type_channel-nominal_text",
    "value": 1,
    "random": 0.0335,
    "structured": 0.08225
  },
  {
    "name": "type_channel-nominal_row",
    "value": 0,
    "random": 0.94705,
    "structured": 0.9249
  },
  {
    "name": "type_channel-nominal_row",
    "value": 1,
    "random": 0.05295,
    "structured": 0.0751
  },
  {
    "name": "type_channel-nominal_column",
    "value": 0,
    "random": 0.94705,
    "structured": 0.9487
  },
  {
    "name": "type_channel-nominal_column",
    "value": 1,
    "random": 0.05295,
    "structured": 0.0513
  },
  {
    "name": "type_channel-temporal_x",
    "value": 0,
    "random": 0.92675,
    "structured": 0.9077
  },
  {
    "name": "type_channel-temporal_x",
    "value": 1,
    "random": 0.07325,
    "structured": 0.0923
  },
  {
    "name": "type_channel-temporal_y",
    "value": 0,
    "random": 0.97005,
    "structured": 0.9421
  },
  {
    "name": "type_channel-temporal_y",
    "value": 1,
    "random": 0.02995,
    "structured": 0.0579
  },
  {
    "name": "type_channel-temporal_color",
    "value": 0,
    "random": 0.96935,
    "structured": 0.9373
  },
  {
    "name": "type_channel-temporal_color",
    "value": 1,
    "random": 0.03065,
    "structured": 0.0627
  },
  {
    "name": "type_channel-temporal_shape",
    "value": 0,
    "random": 1,
    "structured": 1
  },
  {
    "name": "type_channel-temporal_text",
    "value": 0,
    "random": 0.98365,
    "structured": 0.95955
  },
  {
    "name": "type_channel-temporal_text",
    "value": 1,
    "random": 0.01635,
    "structured": 0.04045
  },
  {
    "name": "type_channel-temporal_row",
    "value": 0,
    "random": 1,
    "structured": 1
  },
  {
    "name": "type_channel-temporal_column",
    "value": 0,
    "random": 1,
    "structured": 1
  },
  {
    "name": "aggregate-count",
    "value": 0,
    "random": 0.6844,
    "structured": 0.5773
  },
  {
    "name": "aggregate-count",
    "value": 1,
    "random": 0.30535,
    "structured": 0.41245
  },
  {
    "name": "aggregate-count",
    "value": 3,
    "random": 0.01025,
    "structured": 0.01015
  },
  {
    "name": "aggregate-count",
    "value": 4,
    "random": 0,
    "structured": 0.0001
  },
  {
    "name": "aggregate-sum",
    "value": 0,
    "random": 0.9964,
    "structured": 0.7914
  },
  {
    "name": "aggregate-sum",
    "value": 1,
    "random": 0.00225,
    "structured": 0.16295
  },
  {
    "name": "aggregate-sum",
    "value": 2,
    "random": 0.0013,
    "structured": 0.0369
  },
  {
    "name": "aggregate-sum",
    "value": 3,
    "random": 0.00005,
    "structured": 0.00845
  },
  {
    "name": "aggregate-sum",
    "value": 4,
    "random": 0,
    "structured": 0.0003
  },
  {
    "name": "aggregate-mean",
    "value": 0,
    "random": 0.8806,
    "structured": 0.9438
  },
  {
    "name": "aggregate-mean",
    "value": 1,
    "random": 0.0912,
    "structured": 0.04175
  },
  {
    "name": "aggregate-mean",
    "value": 2,
    "random": 0.02475,
    "structured": 0.0115
  },
  {
    "name": "aggregate-mean",
    "value": 3,
    "random": 0.00315,
    "structured": 0.0029
  },
  {
    "name": "aggregate-mean",
    "value": 4,
    "random": 0.0003,
    "structured": 0.00005
  },
  {
    "name": "aggregate-median",
    "value": 0,
    "random": 0.8501,
    "structured": 0.7337
  },
  {
    "name": "aggregate-median",
    "value": 1,
    "random": 0.0822,
    "structured": 0.1783
  },
  {
    "name": "aggregate-median",
    "value": 2,
    "random": 0.04635,
    "structured": 0.0649
  },
  {
    "name": "aggregate-median",
    "value": 3,
    "random": 0.01805,
    "structured": 0.02235
  },
  {
    "name": "aggregate-median",
    "value": 4,
    "random": 0.0033,
    "structured": 0.00075
  },
  {
    "name": "aggregate-min",
    "value": 0,
    "random": 0.9552,
    "structured": 0.7836
  },
  {
    "name": "aggregate-min",
    "value": 1,
    "random": 0.02885,
    "structured": 0.15325
  },
  {
    "name": "aggregate-min",
    "value": 2,
    "random": 0.0133,
    "structured": 0.04635
  },
  {
    "name": "aggregate-min",
    "value": 3,
    "random": 0.00245,
    "structured": 0.0158
  },
  {
    "name": "aggregate-min",
    "value": 4,
    "random": 0.0002,
    "structured": 0.001
  },
  {
    "name": "aggregate-max",
    "value": 0,
    "random": 0.9996,
    "structured": 0.8875
  },
  {
    "name": "aggregate-max",
    "value": 1,
    "random": 0.0002,
    "structured": 0.07705
  },
  {
    "name": "aggregate-max",
    "value": 2,
    "random": 0.00015,
    "structured": 0.02685
  },
  {
    "name": "aggregate-max",
    "value": 3,
    "random": 0.00005,
    "structured": 0.0081
  },
  {
    "name": "aggregate-max",
    "value": 4,
    "random": 0,
    "structured": 0.0005
  },
  {
    "name": "aggregate-stdev",
    "value": 0,
    "random": 1,
    "structured": 0.9486
  },
  {
    "name": "aggregate-stdev",
    "value": 1,
    "random": 0,
    "structured": 0.0365
  },
  {
    "name": "aggregate-stdev",
    "value": 2,
    "random": 0,
    "structured": 0.011
  },
  {
    "name": "aggregate-stdev",
    "value": 3,
    "random": 0,
    "structured": 0.00365
  },
  {
    "name": "aggregate-stdev",
    "value": 4,
    "random": 0,
    "structured": 0.00025
  },
  {
    "name": "chart-only_x_over_only_y",
    "value": 0,
    "random": 0.95505,
    "structured": 0.9135
  },
  {
    "name": "chart-only_x_over_only_y",
    "value": 1,
    "random": 0.04495,
    "structured": 0.0865
  },
  {
    "name": "chart-binned_one_dimensional",
    "value": 0,
    "random": 0.9786,
    "structured": 0.9991
  },
  {
    "name": "chart-binned_one_dimensional",
    "value": 1,
    "random": 0.0214,
    "structured": 0.0009
  },
  {
    "name": "chart-orientation_horizontal_binned",
    "value": 0,
    "random": 0.8581,
    "structured": 0.833
  },
  {
    "name": "chart-orientation_horizontal_binned",
    "value": 1,
    "random": 0.1419,
    "structured": 0.167
  },
  {
    "name": "chart-one_dim_raw_continuous_tick_over_rest",
    "value": 0,
    "random": 0.9588,
    "structured": 0.99505
  },
  {
    "name": "chart-one_dim_raw_continuous_tick_over_rest",
    "value": 1,
    "random": 0.0412,
    "structured": 0.00495
  },
  {
    "name": "datatype-string_quantitative",
    "value": 0,
    "random": 1,
    "structured": 1
  },
  {
    "name": "datatype-string_ordinal",
    "value": 0,
    "random": 0.754,
    "structured": 0.8631
  },
  {
    "name": "datatype-string_ordinal",
    "value": 1,
    "random": 0.1393,
    "structured": 0.0935
  },
  {
    "name": "datatype-string_ordinal",
    "value": 2,
    "random": 0.0665,
    "structured": 0.03145
  },
  {
    "name": "datatype-string_ordinal",
    "value": 3,
    "random": 0.03345,
    "structured": 0.0115
  },
  {
    "name": "datatype-string_ordinal",
    "value": 4,
    "random": 0.00675,
    "structured": 0.00045
  },
  {
    "name": "datatype-string_nominal",
    "value": 0,
    "random": 0.8764,
    "structured": 0.8588
  },
  {
    "name": "datatype-string_nominal",
    "value": 1,
    "random": 0.0734,
    "structured": 0.11145
  },
  {
    "name": "datatype-string_nominal",
    "value": 2,
    "random": 0.0362,
    "structured": 0.0241
  },
  {
    "name": "datatype-string_nominal",
    "value": 3,
    "random": 0.0135,
    "structured": 0.00555
  },
  {
    "name": "datatype-string_nominal",
    "value": 4,
    "random": 0.0005,
    "structured": 0.0001
  },
  {
    "name": "datatype-string_temporal",
    "value": 0,
    "random": 1,
    "structured": 1
  },
  {
    "name": "datatype-number_quantitative",
    "value": 0,
    "random": 0.7662,
    "structured": 0.7408
  },
  {
    "name": "datatype-number_quantitative",
    "value": 1,
    "random": 0.1207,
    "structured": 0.16965
  },
  {
    "name": "datatype-number_quantitative",
    "value": 2,
    "random": 0.07155,
    "structured": 0.0668
  },
  {
    "name": "datatype-number_quantitative",
    "value": 3,
    "random": 0.0328,
    "structured": 0.0206
  },
  {
    "name": "datatype-number_quantitative",
    "value": 4,
    "random": 0.00875,
    "structured": 0.00215
  },
  {
    "name": "datatype-number_ordinal",
    "value": 0,
    "random": 0.9019,
    "structured": 0.901
  },
  {
    "name": "datatype-number_ordinal",
    "value": 1,
    "random": 0.0636,
    "structured": 0.0695
  },
  {
    "name": "datatype-number_ordinal",
    "value": 2,
    "random": 0.02695,
    "structured": 0.0233
  },
  {
    "name": "datatype-number_ordinal",
    "value": 3,
    "random": 0.00705,
    "structured": 0.006
  },
  {
    "name": "datatype-number_ordinal",
    "value": 4,
    "random": 0.0005,
    "structured": 0.0002
  },
  {
    "name": "datatype-number_nominal",
    "value": 0,
    "random": 0.8911,
    "structured": 0.8934
  },
  {
    "name": "datatype-number_nominal",
    "value": 1,
    "random": 0.07025,
    "structured": 0.08175
  },
  {
    "name": "datatype-number_nominal",
    "value": 2,
    "random": 0.0287,
    "structured": 0.0199
  },
  {
    "name": "datatype-number_nominal",
    "value": 3,
    "random": 0.00945,
    "structured": 0.00475
  },
  {
    "name": "datatype-number_nominal",
    "value": 4,
    "random": 0.0005,
    "structured": 0.0002
  },
  {
    "name": "datatype-number_temporal",
    "value": 0,
    "random": 1,
    "structured": 1
  },
  {
    "name": "datatype-integer_quantitative",
    "value": 0,
    "random": 0.9344,
    "structured": 0.8154
  },
  {
    "name": "datatype-integer_quantitative",
    "value": 1,
    "random": 0.03915,
    "structured": 0.1152
  },
  {
    "name": "datatype-integer_quantitative",
    "value": 2,
    "random": 0.0183,
    "structured": 0.04815
  },
  {
    "name": "datatype-integer_quantitative",
    "value": 3,
    "random": 0.0073,
    "structured": 0.0185
  },
  {
    "name": "datatype-integer_quantitative",
    "value": 4,
    "random": 0.00085,
    "structured": 0.00275
  },
  {
    "name": "datatype-integer_ordinal",
    "value": 0,
    "random": 0.9562,
    "structured": 0.9082
  },
  {
    "name": "datatype-integer_ordinal",
    "value": 1,
    "random": 0.0305,
    "structured": 0.06095
  },
  {
    "name": "datatype-integer_ordinal",
    "value": 2,
    "random": 0.0111,
    "structured": 0.02205
  },
  {
    "name": "datatype-integer_ordinal",
    "value": 3,
    "random": 0.00215,
    "structured": 0.00875
  },
  {
    "name": "datatype-integer_ordinal",
    "value": 4,
    "random": 0.00005,
    "structured": 0.00005
  },
  {
    "name": "datatype-integer_nominal",
    "value": 0,
    "random": 0.9545,
    "structured": 0.9053
  },
  {
    "name": "datatype-integer_nominal",
    "value": 1,
    "random": 0.0312,
    "structured": 0.0692
  },
  {
    "name": "datatype-integer_nominal",
    "value": 2,
    "random": 0.0113,
    "structured": 0.0202
  },
  {
    "name": "datatype-integer_nominal",
    "value": 3,
    "random": 0.00275,
    "structured": 0.00515
  },
  {
    "name": "datatype-integer_nominal",
    "value": 4,
    "random": 0.00025,
    "structured": 0.00015
  },
  {
    "name": "datatype-integer_temporal",
    "value": 0,
    "random": 1,
    "structured": 1
  },
  {
    "name": "datatype-boolean_quantitative",
    "value": 0,
    "random": 1,
    "structured": 1
  },
  {
    "name": "datatype-boolean_ordinal",
    "value": 0,
    "random": 0.9706,
    "structured": 0.9171
  },
  {
    "name": "datatype-boolean_ordinal",
    "value": 1,
    "random": 0.01865,
    "structured": 0.05035
  },
  {
    "name": "datatype-boolean_ordinal",
    "value": 2,
    "random": 0.0082,
    "structured": 0.02305
  },
  {
    "name": "datatype-boolean_ordinal",
    "value": 3,
    "random": 0.00245,
    "structured": 0.00915
  },
  {
    "name": "datatype-boolean_ordinal",
    "value": 4,
    "random": 0.0001,
    "structured": 0.00035
  },
  {
    "name": "datatype-boolean_nominal",
    "value": 0,
    "random": 0.9793,
    "structured": 0.9454
  },
  {
    "name": "datatype-boolean_nominal",
    "value": 1,
    "random": 0.01335,
    "structured": 0.0387
  },
  {
    "name": "datatype-boolean_nominal",
    "value": 2,
    "random": 0.00565,
    "structured": 0.01175
  },
  {
    "name": "datatype-boolean_nominal",
    "value": 3,
    "random": 0.00165,
    "structured": 0.00405
  },
  {
    "name": "datatype-boolean_nominal",
    "value": 4,
    "random": 0.00005,
    "structured": 0.0001
  },
  {
    "name": "datatype-boolean_temporal",
    "value": 0,
    "random": 1,
    "structured": 1
  },
  {
    "name": "datatype-date_quantitative",
    "value": 0,
    "random": 0.873,
    "structured": 0.735
  },
  {
    "name": "datatype-date_quantitative",
    "value": 1,
    "random": 0.07385,
    "structured": 0.1721
  },
  {
    "name": "datatype-date_quantitative",
    "value": 2,
    "random": 0.0365,
    "structured": 0.0659
  },
  {
    "name": "datatype-date_quantitative",
    "value": 3,
    "random": 0.01445,
    "structured": 0.0248
  },
  {
    "name": "datatype-date_quantitative",
    "value": 4,
    "random": 0.0022,
    "structured": 0.0022
  },
  {
    "name": "datatype-date_ordinal",
    "value": 0,
    "random": 0.9286,
    "structured": 0.8898
  },
  {
    "name": "datatype-date_ordinal",
    "value": 1,
    "random": 0.04585,
    "structured": 0.074
  },
  {
    "name": "datatype-date_ordinal",
    "value": 2,
    "random": 0.01995,
    "structured": 0.0275
  },
  {
    "name": "datatype-date_ordinal",
    "value": 3,
    "random": 0.00535,
    "structured": 0.0085
  },
  {
    "name": "datatype-date_ordinal",
    "value": 4,
    "random": 0.00025,
    "structured": 0.0002
  },
  {
    "name": "datatype-date_nominal",
    "value": 0,
    "random": 0.9191,
    "structured": 0.8879
  },
  {
    "name": "datatype-date_nominal",
    "value": 1,
    "random": 0.05435,
    "structured": 0.0846
  },
  {
    "name": "datatype-date_nominal",
    "value": 2,
    "random": 0.0219,
    "structured": 0.0228
  },
  {
    "name": "datatype-date_nominal",
    "value": 3,
    "random": 0.0044,
    "structured": 0.0047
  },
  {
    "name": "datatype-date_temporal",
    "value": 0,
    "random": 0.8824,
    "structured": 0.7888
  },
  {
    "name": "datatype-date_temporal",
    "value": 1,
    "random": 0.08215,
    "structured": 0.16255
  },
  {
    "name": "datatype-date_temporal",
    "value": 2,
    "random": 0.0295,
    "structured": 0.03765
  },
  {
    "name": "datatype-date_temporal",
    "value": 3,
    "random": 0.00565,
    "structured": 0.01
  },
  {
    "name": "datatype-date_temporal",
    "value": 4,
    "random": 0.0003,
    "structured": 0.001
  },
  {
    "name": "datatype-high_cardinality_ordinal",
    "value": 0,
    "random": 0.7763,
    "structured": 0.7604
  },
  {
    "name": "datatype-high_cardinality_ordinal",
    "value": 1,
    "random": 0.13195,
    "structured": 0.15995
  },
  {
    "name": "datatype-high_cardinality_ordinal",
    "value": 2,
    "random": 0.0668,
    "structured": 0.0613
  },
  {
    "name": "datatype-high_cardinality_ordinal",
    "value": 3,
    "random": 0.02195,
    "structured": 0.01795
  },
  {
    "name": "datatype-high_cardinality_ordinal",
    "value": 4,
    "random": 0.003,
    "structured": 0.0004
  },
  {
    "name": "datatype-high_cardinality_nominal",
    "value": 0,
    "random": 0.7705,
    "structured": 0.7212
  },
  {
    "name": "datatype-high_cardinality_nominal",
    "value": 1,
    "random": 0.1451,
    "structured": 0.20655
  },
  {
    "name": "datatype-high_cardinality_nominal",
    "value": 2,
    "random": 0.0629,
    "structured": 0.05935
  },
  {
    "name": "datatype-high_cardinality_nominal",
    "value": 3,
    "random": 0.0202,
    "structured": 0.0127
  },
  {
    "name": "datatype-high_cardinality_nominal",
    "value": 4,
    "random": 0.0013,
    "structured": 0.0002
  },
  {
    "name": "datatype-high_cardinality_nominal_color",
    "value": 0,
    "random": 1,
    "structured": 1
  },
  {
    "name": "datatype-high_cardinality_size",
    "value": 0,
    "random": 1,
    "structured": 1
  },
  {
    "name": "encoding-encoding",
    "value": 1,
    "random": 0.2531,
    "structured": 0.0174
  },
  {
    "name": "encoding-encoding",
    "value": 2,
    "random": 0.2504,
    "structured": 0.2071
  },
  {
    "name": "encoding-encoding",
    "value": 3,
    "random": 0.2505,
    "structured": 0.382
  },
  {
    "name": "encoding-encoding",
    "value": 4,
    "random": 0.246,
    "structured": 0.3935
  },
  {
    "name": "encoding-encoding_field",
    "value": 0,
    "random": 0.0064,
    "structured": 0.001
  },
  {
    "name": "encoding-encoding_field",
    "value": 1,
    "random": 0.314,
    "structured": 0.06905
  },
  {
    "name": "encoding-encoding_field",
    "value": 2,
    "random": 0.2981,
    "structured": 0.33125
  },
  {
    "name": "encoding-encoding_field",
    "value": 3,
    "random": 0.2829,
    "structured": 0.41805
  },
  {
    "name": "encoding-encoding_field",
    "value": 4,
    "random": 0.0986,
    "structured": 0.18065
  },
  {
    "name": "encoding-aggregate",
    "value": 0,
    "random": 0.45725,
    "structured": 0.1361
  },
  {
    "name": "encoding-aggregate",
    "value": 1,
    "random": 0.3789,
    "structured": 0.34745
  },
  {
    "name": "encoding-aggregate",
    "value": 2,
    "random": 0.0909,
    "structured": 0.27735
  },
  {
    "name": "encoding-aggregate",
    "value": 3,
    "random": 0.05355,
    "structured": 0.1753
  },
  {
    "name": "encoding-aggregate",
    "value": 4,
    "random": 0.0194,
    "structured": 0.0638
  },
  {
    "name": "encoding-bin",
    "value": 0,
    "random": 0.7935,
    "structured": 0.6335
  },
  {
    "name": "encoding-bin",
    "value": 1,
    "random": 0.12535,
    "structured": 0.24865
  },
  {
    "name": "encoding-bin",
    "value": 2,
    "random": 0.0595,
    "structured": 0.0871
  },
  {
    "name": "encoding-bin",
    "value": 3,
    "random": 0.0196,
    "structured": 0.0297
  },
  {
    "name": "encoding-bin",
    "value": 4,
    "random": 0.00205,
    "structured": 0.00105
  },
  {
    "name": "encoding-same_field_2",
    "value": 0,
    "random": 0.60415,
    "structured": 0.61965
  },
  {
    "name": "encoding-same_field_2",
    "value": 1,
    "random": 0.3791,
    "structured": 0.3644
  },
  {
    "name": "encoding-same_field_2",
    "value": 2,
    "random": 0.01675,
    "structured": 0.01595
  },
  {
    "name": "encoding-same_field_gte3",
    "value": 0,
    "random": 0.9263,
    "structured": 0.88565
  },
  {
    "name": "encoding-same_field_gte3",
    "value": 1,
    "random": 0.0737,
    "structured": 0.11435
  },
  {
    "name": "encoding-count_twice",
    "value": 0,
    "random": 0.98975,
    "structured": 0.98975
  },
  {
    "name": "encoding-count_twice",
    "value": 1,
    "random": 0.01025,
    "structured": 0.01025
  },
  {
    "name": "encoding-quant_bin",
    "value": 0,
    "random": 0.9678,
    "structured": 0.8283
  },
  {
    "name": "encoding-quant_bin",
    "value": 1,
    "random": 0.02035,
    "structured": 0.1184
  },
  {
    "name": "encoding-quant_bin",
    "value": 2,
    "random": 0.0093,
    "structured": 0.04075
  },
  {
    "name": "encoding-quant_bin",
    "value": 3,
    "random": 0.00245,
    "structured": 0.0121
  },
  {
    "name": "encoding-quant_bin",
    "value": 4,
    "random": 0.0001,
    "structured": 0.00045
  },
  {
    "name": "encoding-non_positional_pref",
    "value": 0,
    "random": 0.7971,
    "structured": 0.7459
  },
  {
    "name": "encoding-non_positional_pref",
    "value": 1,
    "random": 0.2029,
    "structured": 0.2541
  },
  {
    "name": "encoding-multiple_non_pos",
    "value": 0,
    "random": 0.82535,
    "structured": 0.6456
  },
  {
    "name": "encoding-multiple_non_pos",
    "value": 1,
    "random": 0.17465,
    "structured": 0.3544
  },
  {
    "name": "encoding-aggregate_group_by_raw_non_temporal",
    "value": 0,
    "random": 0.9021,
    "structured": 0.898
  },
  {
    "name": "encoding-aggregate_group_by_raw_non_temporal",
    "value": 1,
    "random": 0.05265,
    "structured": 0.08255
  },
  {
    "name": "encoding-aggregate_group_by_raw_non_temporal",
    "value": 2,
    "random": 0.03375,
    "structured": 0.0167
  },
  {
    "name": "encoding-aggregate_group_by_raw_non_temporal",
    "value": 3,
    "random": 0.0115,
    "structured": 0.00275
  },
  {
    "name": "encoding-agg_dim",
    "value": 0,
    "random": 0.9168,
    "structured": 0.912
  },
  {
    "name": "encoding-agg_dim",
    "value": 1,
    "random": 0.0832,
    "structured": 0.088
  },
  {
    "name": "encoding-x_y_raw",
    "value": 0,
    "random": 0.9939,
    "structured": 0.9789
  },
  {
    "name": "encoding-x_y_raw",
    "value": 1,
    "random": 0.00515,
    "structured": 0.02
  },
  {
    "name": "encoding-x_y_raw",
    "value": 2,
    "random": 0.00095,
    "structured": 0.0011
  },
  {
    "name": "encoding-stack_zero",
    "value": 0,
    "random": 0.99665,
    "structured": 0.9653
  },
  {
    "name": "encoding-stack_zero",
    "value": 1,
    "random": 0.00335,
    "structured": 0.0347
  },
  {
    "name": "encoding-stack_normalize",
    "value": 0,
    "random": 0.9953,
    "structured": 0.9829
  },
  {
    "name": "encoding-stack_normalize",
    "value": 1,
    "random": 0.0047,
    "structured": 0.0171
  },
  {
    "name": "encoding-type_quantitative",
    "value": 0,
    "random": 0.39885,
    "structured": 0.1418
  },
  {
    "name": "encoding-type_quantitative",
    "value": 1,
    "random": 0.3396,
    "structured": 0.43095
  },
  {
    "name": "encoding-type_quantitative",
    "value": 2,
    "random": 0.1322,
    "structured": 0.26225
  },
  {
    "name": "encoding-type_quantitative",
    "value": 3,
    "random": 0.08805,
    "structured": 0.1334
  },
  {
    "name": "encoding-type_quantitative",
    "value": 4,
    "random": 0.0413,
    "structured": 0.0316
  },
  {
    "name": "encoding-type_ordinal",
    "value": 0,
    "random": 0.5327,
    "structured": 0.4963
  },
  {
    "name": "encoding-type_ordinal",
    "value": 1,
    "random": 0.268,
    "structured": 0.3191
  },
  {
    "name": "encoding-type_ordinal",
    "value": 2,
    "random": 0.1304,
    "structured": 0.1348
  },
  {
    "name": "encoding-type_ordinal",
    "value": 3,
    "random": 0.05915,
    "structured": 0.0482
  },
  {
    "name": "encoding-type_ordinal",
    "value": 4,
    "random": 0.00975,
    "structured": 0.0016
  },
  {
    "name": "encoding-type_nominal",
    "value": 0,
    "random": 0.6359,
    "structured": 0.5025
  },
  {
    "name": "encoding-type_nominal",
    "value": 1,
    "random": 0.2209,
    "structured": 0.3651
  },
  {
    "name": "encoding-type_nominal",
    "value": 2,
    "random": 0.10195,
    "structured": 0.1051
  },
  {
    "name": "encoding-type_nominal",
    "value": 3,
    "random": 0.0383,
    "structured": 0.0265
  },
  {
    "name": "encoding-type_nominal",
    "value": 4,
    "random": 0.00295,
    "structured": 0.0008
  },
  {
    "name": "mark_type-c_c_point",
    "value": 0,
    "random": 0.94855,
    "structured": 0.93605
  },
  {
    "name": "mark_type-c_c_point",
    "value": 1,
    "random": 0.05145,
    "structured": 0.06395
  },
  {
    "name": "mark_type-c_c_circle",
    "value": 0,
    "random": 1,
    "structured": 1
  },
  {
    "name": "mark_type-c_c_square",
    "value": 0,
    "random": 1,
    "structured": 1
  },
  {
    "name": "mark_type-c_c_line",
    "value": 0,
    "random": 0.97895,
    "structured": 0.97515
  },
  {
    "name": "mark_type-c_c_line",
    "value": 1,
    "random": 0.02105,
    "structured": 0.02485
  },
  {
    "name": "mark_type-c_c_area",
    "value": 0,
    "random": 1,
    "structured": 1
  },
  {
    "name": "mark_type-c_c_text",
    "value": 0,
    "random": 0.99145,
    "structured": 0.96165
  },
  {
    "name": "mark_type-c_c_text",
    "value": 1,
    "random": 0.00855,
    "structured": 0.03835
  },
  {
    "name": "mark_type-c_c_tick",
    "value": 0,
    "random": 1,
    "structured": 1
  },
  {
    "name": "mark_type-c_d_point",
    "value": 0,
    "random": 0.8932,
    "structured": 0.89195
  },
  {
    "name": "mark_type-c_d_point",
    "value": 1,
    "random": 0.1068,
    "structured": 0.10805
  },
  {
    "name": "mark_type-c_d_bar",
    "value": 0,
    "random": 1,
    "structured": 1
  },
  {
    "name": "mark_type-c_d_line",
    "value": 0,
    "random": 0.9978,
    "structured": 0.9657
  },
  {
    "name": "mark_type-c_d_line",
    "value": 1,
    "random": 0.0022,
    "structured": 0.0343
  },
  {
    "name": "mark_type-c_d_area",
    "value": 0,
    "random": 1,
    "structured": 1
  },
  {
    "name": "mark_type-c_d_text",
    "value": 0,
    "random": 0.9857,
    "structured": 0.94485
  },
  {
    "name": "mark_type-c_d_text",
    "value": 1,
    "random": 0.0143,
    "structured": 0.05515
  },
  {
    "name": "mark_type-c_d_tick",
    "value": 0,
    "random": 0.9982,
    "structured": 0.9689
  },
  {
    "name": "mark_type-c_d_tick",
    "value": 1,
    "random": 0.0018,
    "structured": 0.0311
  },
  {
    "name": "mark_type-c_d_no_overlap_point",
    "value": 0,
    "random": 0.84725,
    "structured": 0.92205
  },
  {
    "name": "mark_type-c_d_no_overlap_point",
    "value": 1,
    "random": 0.15275,
    "structured": 0.07795
  },
  {
    "name": "mark_type-c_d_no_overlap_bar",
    "value": 0,
    "random": 0.984,
    "structured": 0.9428
  },
  {
    "name": "mark_type-c_d_no_overlap_bar",
    "value": 1,
    "random": 0.016,
    "structured": 0.0572
  },
  {
    "name": "mark_type-c_d_no_overlap_line",
    "value": 0,
    "random": 0.99745,
    "structured": 0.97255
  },
  {
    "name": "mark_type-c_d_no_overlap_line",
    "value": 1,
    "random": 0.00255,
    "structured": 0.02745
  },
  {
    "name": "mark_type-c_d_no_overlap_area",
    "value": 0,
    "random": 0.9965,
    "structured": 0.97205
  },
  {
    "name": "mark_type-c_d_no_overlap_area",
    "value": 1,
    "random": 0.0035,
    "structured": 0.02795
  },
  {
    "name": "mark_type-c_d_no_overlap_text",
    "value": 0,
    "random": 0.9963,
    "structured": 0.96215
  },
  {
    "name": "mark_type-c_d_no_overlap_text",
    "value": 1,
    "random": 0.0037,
    "structured": 0.03785
  },
  {
    "name": "mark_type-c_d_no_overlap_tick",
    "value": 0,
    "random": 0.99755,
    "structured": 0.97085
  },
  {
    "name": "mark_type-c_d_no_overlap_tick",
    "value": 1,
    "random": 0.00245,
    "structured": 0.02915
  },
  {
    "name": "mark_type-d_d_point",
    "value": 0,
    "random": 0.85095,
    "structured": 0.9403
  },
  {
    "name": "mark_type-d_d_point",
    "value": 1,
    "random": 0.14905,
    "structured": 0.0597
  },
  {
    "name": "mark_type-d_d_text",
    "value": 0,
    "random": 0.97985,
    "structured": 0.96285
  },
  {
    "name": "mark_type-d_d_text",
    "value": 1,
    "random": 0.02015,
    "structured": 0.03715
  },
  {
    "name": "mark_type-d_d_rect",
    "value": 0,
    "random": 1,
    "structured": 1
  },
  {
    "name": "scale-log",
    "value": 0,
    "random": 1,
    "structured": 0.39265
  },
  {
    "name": "scale-log",
    "value": 1,
    "random": 0,
    "structured": 0.39815
  },
  {
    "name": "scale-log",
    "value": 2,
    "random": 0,
    "structured": 0.14175
  },
  {
    "name": "scale-log",
    "value": 3,
    "random": 0,
    "structured": 0.0592
  },
  {
    "name": "scale-log",
    "value": 4,
    "random": 0,
    "structured": 0.00825
  },
  {
    "name": "scale-zero",
    "value": 0,
    "random": 0.5153,
    "structured": 0.2477
  },
  {
    "name": "scale-zero",
    "value": 1,
    "random": 0.3424,
    "structured": 0.4481
  },
  {
    "name": "scale-zero",
    "value": 2,
    "random": 0.0854,
    "structured": 0.2145
  },
  {
    "name": "scale-zero",
    "value": 3,
    "random": 0.0471,
    "structured": 0.079
  },
  {
    "name": "scale-zero",
    "value": 4,
    "random": 0.0098,
    "structured": 0.0107
  },
  {
    "name": "scale-zero_bin",
    "value": 0,
    "random": 1,
    "structured": 1
  },
  {
    "name": "scale-zero_size",
    "value": 0,
    "random": 0.87605,
    "structured": 0.74455
  },
  {
    "name": "scale-zero_size",
    "value": 1,
    "random": 0.12395,
    "structured": 0.25545
  },
  {
    "name": "scale-zero_positional",
    "value": 0,
    "random": 0.65125,
    "structured": 0.4242
  },
  {
    "name": "scale-zero_positional",
    "value": 1,
    "random": 0.34875,
    "structured": 0.5758
  },
  {
    "name": "scale-zero_skew",
    "value": 0,
    "random": 0.92915,
    "structured": 0.8733
  },
  {
    "name": "scale-zero_skew",
    "value": 1,
    "random": 0.07085,
    "structured": 0.1267
  },
  {
    "name": "scale-includes_zero",
    "value": 0,
    "random": 0.9407,
    "structured": 0.89905
  },
  {
    "name": "scale-includes_zero",
    "value": 1,
    "random": 0.0506,
    "structured": 0.0886
  },
  {
    "name": "scale-includes_zero",
    "value": 2,
    "random": 0.00745,
    "structured": 0.0115
  },
  {
    "name": "scale-includes_zero",
    "value": 3,
    "random": 0.00125,
    "structured": 0.0008
  },
  {
    "name": "scale-includes_zero",
    "value": 4,
    "random": 0,
    "structured": 0.00005
  },
  {
    "name": "type_channel-continuous_x",
    "value": 0,
    "random": 0.6206,
    "structured": 0.4395
  },
  {
    "name": "type_channel-continuous_x",
    "value": 1,
    "random": 0.3794,
    "structured": 0.5605
  },
  {
    "name": "type_channel-continuous_y",
    "value": 0,
    "random": 0.8208,
    "structured": 0.66985
  },
  {
    "name": "type_channel-continuous_y",
    "value": 1,
    "random": 0.1792,
    "structured": 0.33015
  },
  {
    "name": "type_channel-continuous_color",
    "value": 0,
    "random": 0.773,
    "structured": 0.68105
  },
  {
    "name": "type_channel-continuous_color",
    "value": 1,
    "random": 0.227,
    "structured": 0.31895
  },
  {
    "name": "type_channel-continuous_size",
    "value": 0,
    "random": 0.9056,
    "structured": 0.8616
  },
  {
    "name": "type_channel-continuous_size",
    "value": 1,
    "random": 0.0944,
    "structured": 0.1384
  },
  {
    "name": "type_channel-continuous_text",
    "value": 0,
    "random": 0.952,
    "structured": 0.87225
  },
  {
    "name": "type_channel-continuous_text",
    "value": 1,
    "random": 0.048,
    "structured": 0.12775
  },
  {
    "name": "type_channel-ordered_x",
    "value": 0,
    "random": 0.6638,
    "structured": 0.79755
  },
  {
    "name": "type_channel-ordered_x",
    "value": 1,
    "random": 0.3362,
    "structured": 0.20245
  },
  {
    "name": "type_channel-ordered_y",
    "value": 0,
    "random": 0.72065,
    "structured": 0.7039
  },
  {
    "name": "type_channel-ordered_y",
    "value": 1,
    "random": 0.27935,
    "structured": 0.2961
  },
  {
    "name": "type_channel-ordered_color",
    "value": 0,
    "random": 0.9296,
    "structured": 0.87085
  },
  {
    "name": "type_channel-ordered_color",
    "value": 1,
    "random": 0.0704,
    "structured": 0.12915
  },
  {
    "name": "type_channel-ordered_size",
    "value": 0,
    "random": 0.95195,
    "structured": 0.86725
  },
  {
    "name": "type_channel-ordered_size",
    "value": 1,
    "random": 0.04805,
    "structured": 0.13275
  },
  {
    "name": "type_channel-ordered_text",
    "value": 0,
    "random": 0.9381,
    "structured": 0.89795
  },
  {
    "name": "type_channel-ordered_text",
    "value": 1,
    "random": 0.0619,
    "structured": 0.10205
  },
  {
    "name": "type_channel-ordered_row",
    "value": 0,
    "random": 0.88745,
    "structured": 0.89355
  },
  {
    "name": "type_channel-ordered_row",
    "value": 1,
    "random": 0.11255,
    "structured": 0.10645
  },
  {
    "name": "type_channel-ordered_column",
    "value": 0,
    "random": 0.89855,
    "structured": 0.9511
  },
  {
    "name": "type_channel-ordered_column",
    "value": 1,
    "random": 0.10145,
    "structured": 0.0489
  },
  {
    "name": "type_channel-nominal_x",
    "value": 0,
    "random": 0.8118,
    "structured": 0.88245
  },
  {
    "name": "type_channel-nominal_x",
    "value": 1,
    "random": 0.1882,
    "structured": 0.11755
  },
  {
    "name": "type_channel-nominal_y",
    "value": 0,
    "random": 0.8573,
    "structured": 0.8296
  },
  {
    "name": "type_channel-nominal_y",
    "value": 1,
    "random": 0.1427,
    "structured": 0.1704
  },
  {
    "name": "type_channel-nominal_color",
    "value": 0,
    "random": 0.96955,
    "structured": 0.9059
  },
  {
    "name": "type_channel-nominal_color",
    "value": 1,
    "random": 0.03045,
    "structured": 0.0941
  },
  {
    "name": "type_channel-nominal_shape",
    "value": 0,
    "random": 0.9812,
    "structured": 0.9601
  },
  {
    "name": "type_channel-nominal_shape",
    "value": 1,
    "random": 0.0188,
    "structured": 0.0399
  },
  {
    "name": "type_channel-nominal_text",
    "value": 0,
    "random": 0.9665,
    "structured": 0.91775
  },
  {
    "name": "type_channel-nominal_text",
    "value": 1,
    "random": 0.0335,
    "structured": 0.08225
  },
  {
    "name": "type_channel-nominal_row",
    "value": 0,
    "random": 0.94705,
    "structured": 0.9249
  },
  {
    "name": "type_channel-nominal_row",
    "value": 1,
    "random": 0.05295,
    "structured": 0.0751
  },
  {
    "name": "type_channel-nominal_column",
    "value": 0,
    "random": 0.94705,
    "structured": 0.9487
  },
  {
    "name": "type_channel-nominal_column",
    "value": 1,
    "random": 0.05295,
    "structured": 0.0513
  },
  {
    "name": "type_channel-temporal_x",
    "value": 0,
    "random": 0.92675,
    "structured": 0.9077
  },
  {
    "name": "type_channel-temporal_x",
    "value": 1,
    "random": 0.07325,
    "structured": 0.0923
  },
  {
    "name": "type_channel-temporal_y",
    "value": 0,
    "random": 0.97005,
    "structured": 0.9421
  },
  {
    "name": "type_channel-temporal_y",
    "value": 1,
    "random": 0.02995,
    "structured": 0.0579
  },
  {
    "name": "type_channel-temporal_color",
    "value": 0,
    "random": 0.96935,
    "structured": 0.9373
  },
  {
    "name": "type_channel-temporal_color",
    "value": 1,
    "random": 0.03065,
    "structured": 0.0627
  },
  {
    "name": "type_channel-temporal_shape",
    "value": 0,
    "random": 1,
    "structured": 1
  },
  {
    "name": "type_channel-temporal_text",
    "value": 0,
    "random": 0.98365,
    "structured": 0.95955
  },
  {
    "name": "type_channel-temporal_text",
    "value": 1,
    "random": 0.01635,
    "structured": 0.04045
  },
  {
    "name": "type_channel-temporal_row",
    "value": 0,
    "random": 1,
    "structured": 1
  },
  {
    "name": "type_channel-temporal_column",
    "value": 0,
    "random": 1,
    "structured": 1
  }
]